utils/__init__.py
utils/common.py
utils/data_mgmt.py
utils/model.py
ANN_Implementation_kkkumar2-0.0.2.dist-info/LICENSE
ANN_Implementation_kkkumar2-0.0.2.dist-info/METADATA
ANN_Implementation_kkkumar2-0.0.2.dist-info/WHEEL
ANN_Implementation_kkkumar2-0.0.2.dist-info/top_level.txt
ANN_Implementation_kkkumar2-0.0.2.dist-info/RECORD
