Metadata-Version: 2.1
Name: ANN-Implementation-kkkumar2
Version: 0.0.2
Summary: This is a ANN using Tensorflow package
Home-page: https://github.com/kkkumar2/ANN---Implementation
Author: kkkumar2
Author-email: kmohankumar123456@gmail.com
License: UNKNOWN
Project-URL: Bug Tracker, https://github.com/kkkumar2/ANN---Implementation
Platform: UNKNOWN
Classifier: Programming Language :: Python :: 3
Classifier: License :: OSI Approved :: MIT License
Classifier: Operating System :: OS Independent
Requires-Python: >=3.7
License-File: LICENSE
Requires-Dist: numpy
Requires-Dist: tqdm
Requires-Dist: pandas
Requires-Dist: matplotlib
Requires-Dist: tensorflow
Requires-Dist: seaborn
